LICENSE
README.md
pyproject.toml
setup.py
disksurf/__init__.py
disksurf/observation.py
disksurf/surface.py
disksurf.egg-info/PKG-INFO
disksurf.egg-info/SOURCES.txt
disksurf.egg-info/dependency_links.txt
disksurf.egg-info/requires.txt
disksurf.egg-info/top_level.txt