Metadata-Version: 2.1
Name: disksurf
Version: 1.2.6
Summary: Infer and reproject a disk's 3D structure.
Home-page: https://github.com/richteague/disksurf
Author: Richard Teague
Author-email: rteague@mit.edu
License: MIT
Classifier: Programming Language :: Python :: 3.5
Classifier: License :: OSI Approved :: MIT License
Classifier: Operating System :: OS Independent
License-File: LICENSE
